{
  "bird feeding station": 1.0,
  "bird feeder": 0.7,
  "wild bird feeding station": 0.65,
  "garden kneeler seat": 1.0,
  "kneeler seat handles": 0.95,
  "kneeler seat wheels": 0.75,
  "garden kneeler elderly": 0.95,
  "garden kneeler seniors": 0.85,
  "heavy duty kneeler": 0.65,
  "kneeler tool set": 1.0,
  "easy grip tools": 1.0,
  "feeding station roof": 0.8,
  "bird feeder baffle": 0.7,
  "feeding station base": 0.85,
  "wild bird feeder": 0.65,
  "reading magnifier light": 1.0,
  "magnifying glass light": 0.95,
  "magnifier lamp": 0.9,
  "magnifier light stand": 0.75,
  "reader magnifier light": 0.7,
  "support seat cushion": 1.0,
  "elderly seat cushion": 0.95,
  "sofa cushion support": 0.9,
  "car seat cushion": 0.85,
  "baby seat cushion": 0.8,
  "chair cushion support": 0.75,
  "back support cushion": 0.9,
  "lumbar support cushion": 0.95,
  "lumbar cushion buttocks": 0.8,
  "lumbar cushion elderly": 0.75,
  "lumbar cushion driving": 0.7,
  "back pain cushion": 0.65,
  "memory foam cushion set": 1.0,
  "cordless garden tools": 1.0,
  "cordless tools bundle": 0.95,
  "cordless tool set": 1.0,
  "cordless tool system": 1.0,
  "cordless tool range": 0.9,
  "battery tool set": 0.95,
  "cordless yard tools": 0.9,
  "power tool set": 0.85,
  "multi tool set": 0.75,
  "battery tool kit": 0.65
}